LICENSE
README.md
setup.cfg
setup.py
USJ_dsptools.egg-info/PKG-INFO
USJ_dsptools.egg-info/SOURCES.txt
USJ_dsptools.egg-info/dependency_links.txt
USJ_dsptools.egg-info/not-zip-safe
USJ_dsptools.egg-info/requires.txt
USJ_dsptools.egg-info/top_level.txt
dsptools/__init__.py
dsptools/frequency.py
dsptools/graph.py
dsptools/operations.py
dsptools/ztransform.py